README
setup.py
adspygoogle/__init__.py
adspygoogle.dfp.egg-info/PKG-INFO
adspygoogle.dfp.egg-info/SOURCES.txt
adspygoogle.dfp.egg-info/dependency_links.txt
adspygoogle.dfp.egg-info/requires.txt
adspygoogle.dfp.egg-info/top_level.txt
adspygoogle/SOAPpy/Client.py
adspygoogle/SOAPpy/Config.py
adspygoogle/SOAPpy/Errors.py
adspygoogle/SOAPpy/NS.py
adspygoogle/SOAPpy/Parser.py
adspygoogle/SOAPpy/SOAP.py
adspygoogle/SOAPpy/SOAPBuilder.py
adspygoogle/SOAPpy/Server.py
adspygoogle/SOAPpy/Types.py
adspygoogle/SOAPpy/URLopener.py
adspygoogle/SOAPpy/Utilities.py
adspygoogle/SOAPpy/WSDL.py
adspygoogle/SOAPpy/__init__.py
adspygoogle/SOAPpy/download_and_patch_soappy.py
adspygoogle/SOAPpy/version.py
adspygoogle/SOAPpy/wstools/Namespaces.py
adspygoogle/SOAPpy/wstools/TimeoutSocket.py
adspygoogle/SOAPpy/wstools/UserTuple.py
adspygoogle/SOAPpy/wstools/Utility.py
adspygoogle/SOAPpy/wstools/WSDLTools.py
adspygoogle/SOAPpy/wstools/XMLSchema.py
adspygoogle/SOAPpy/wstools/XMLname.py
adspygoogle/SOAPpy/wstools/__init__.py
adspygoogle/SOAPpy/wstools/c14n.py
adspygoogle/SOAPpy/wstools/logging.py
adspygoogle/common/AuthToken.py
adspygoogle/common/Buffer.py
adspygoogle/common/Client.py
adspygoogle/common/Errors.py
adspygoogle/common/GenericApiService.py
adspygoogle/common/Logger.py
adspygoogle/common/MessageHandler.py
adspygoogle/common/SanityCheck.py
adspygoogle/common/SoapBuffer.py
adspygoogle/common/Utils.py
adspygoogle/common/__init__.py
adspygoogle/common/https/Https.py
adspygoogle/common/https/__init__.py
adspygoogle/common/soappy/SoappyUtils.py
adspygoogle/common/soappy/__init__.py
adspygoogle/dfp/DfpClient.py
adspygoogle/dfp/DfpErrors.py
adspygoogle/dfp/DfpSanityCheck.py
adspygoogle/dfp/DfpSoapBuffer.py
adspygoogle/dfp/DfpUtils.py
adspygoogle/dfp/GenericDfpService.py
adspygoogle/dfp/__init__.py
adspygoogle/dfp/data/currencies.csv
adspygoogle/dfp/data/error_types.csv
adspygoogle/dfp/data/timezones.csv
scripts/adspygoogle_generate_refresh_token.py
scripts/dfp_config.py