Metadata-Version: 1.0
Name: adspygoogle.dfp
Version: 9.8.0
Summary: DFP API Python Client Library
Home-page: http://code.google.com/p/google-api-ads-python
Author: Vincent Tsao
Author-email: UNKNOWN
License: Apache License 2.0
Platform: any
